infi.mount_utils-0.0.10-py2.7-nspkg.pth
infi/mount_utils/__init__.py
infi/mount_utils/__version__.py
infi/mount_utils/exceptions.py
infi/mount_utils/base/__init__.py
infi/mount_utils/base/mounter.py
infi/mount_utils/base/supported_fs.py
infi/mount_utils/base/mount/__init__.py
infi/mount_utils/base/mount/entry.py
infi/mount_utils/base/mount/repository.py
infi/mount_utils/linux/__init__.py
infi/mount_utils/linux/mounter.py
infi/mount_utils/linux/supported_fs.py
infi/mount_utils/linux/mount/__init__.py
infi/mount_utils/linux/mount/repository.py
infi/mount_utils/solaris/__init__.py
infi/mount_utils/solaris/mounter.py
infi/mount_utils/solaris/supported_fs.py
infi/mount_utils/solaris/mount/__init__.py
infi/mount_utils/solaris/mount/entry.py
infi/mount_utils/solaris/mount/repository.py
infi.mount_utils-0.0.10.dist-info/LICENSE
infi.mount_utils-0.0.10.dist-info/METADATA
infi.mount_utils-0.0.10.dist-info/WHEEL
infi.mount_utils-0.0.10.dist-info/entry_points.txt
infi.mount_utils-0.0.10.dist-info/namespace_packages.txt
infi.mount_utils-0.0.10.dist-info/top_level.txt
infi.mount_utils-0.0.10.dist-info/RECORD
