Metadata-Version: 2.1
Name: infi.mount-utils
Version: 0.0.10
Summary: Python bindings/wrappers for mounting devices
Home-page: https://git.infinidat.com/host-opensource/infi.mount_utils
Author: Arnon Yaari
Author-email: arnony@infinidat.com
License: BSD
Platform: UNKNOWN
Classifier: Intended Audience :: Developers
Classifier: Intended Audience :: System Administrators
Classifier: License :: OSI Approved :: BSD License
Classifier: Operating System :: OS Independent
Classifier: Programming Language :: Python
Classifier: Programming Language :: Python :: 2
Classifier: Programming Language :: Python :: 3
Classifier: Topic :: Software Development :: Libraries :: Python Modules
Requires-Dist: Brownie
Requires-Dist: infi.exceptools
Requires-Dist: infi.execute
Requires-Dist: infi.os-info
Requires-Dist: infi.pyutils
Requires-Dist: munch
Requires-Dist: setuptools
